{
  "marathi": {
    "June": {
      "topic": "वर्ग पूर्वतयारी अभ्यासक्रम ( अध्ययन निष्पत्ती क्रमांक) \n१. अजान आम्ही तुझी लेकरे (प्रार्थना ) \nआमचे खेळ (चित्रवर्णन ).   ९.३ / ९.३.२ /९.४ \n२. पाऊस (कविता ).   ९.१ / ९.१.२ /९.२",
      "objectives": "संकल्पना व उद्दिष्टे सराव.",
      "activity": "विविध कृती व उपक्रम."
    },
    "July": {
      "topic": "३. साबणाचे बुडबुडे.   १०.४ \nसराव व उजळणी \n४. अशी झाली फजिती   ९.३ / १०.५.२ / १०.८ .३ \n५ . लपाछपी         १०.४ /१०.८.२",
      "objectives": "संकल्पना व उद्दिष्टे सराव.",
      "activity": "विविध कृती व उपक्रम."
    },
    "August": {
      "topic": "६. लिहावे नाटक.       ९.३ / १०.४ / १०.८.४ \nप्रथम घटक चाचणी \n७. आकाशातील तारे.      ८. पवनचक्की \n९. भाज्यांची शाळा   (कविता ).   ९.१ /९.१.२ / ९.२",
      "objectives": "संकल्पना व उद्दिष्टे सराव.",
      "activity": "विविध कृती व उपक्रम."
    },
    "September": {
      "topic": "१०. एक राखी सैनिकासाठी \nकबूतर आणि मुंगी (चित्रकथा )   ११. बागेतील फेरफटका \n१२. एक झाड लावू ,मित्रा!  ( कविता)९.१ /९.१.२ /९.२ \nप्रथम सत्र संकलित मूल्यमापन क्र.१",
      "objectives": "संकल्पना व उद्दिष्टे सराव.",
      "activity": "विविध कृती व उपक्रम."
    },
    "October": {
      "topic": "अतिरिक्त पूरक मार्गदर्शन तसेच सराव \nदिवाळी सुट्ट्या \nसराव व उजळणी \nदिवाळी  (चित्रवर्णन) ९.३ /९.३.२ / ९.४",
      "objectives": "संकल्पना व उद्दिष्टे सराव.",
      "activity": "विविध कृती व उपक्रम."
    },
    "November": {
      "topic": "१३. बैलजोडी (कविता).        ९.१ / ९.१.२ / ९.२ \n१४. अदितीचे साहस \n१५. मासा (कविता ).       ९.१ /९.१.२ /९.२ \nसराव व उजळणी",
      "objectives": "संकल्पना व उद्दिष्टे सराव.",
      "activity": "विविध कृती व उपक्रम."
    },
    "December": {
      "topic": "१६. मारियाचे स्वप्न \n१७. आभाळाचा फळा (कविता ) ९.१ / ९.१.२ / ९.२ \n१८. चांदोबाचा अंगरखा  १९.शाळा (कविता ) ९.१ /९.१.२ / ९.२ \nद्वितीय घटक चाचणी",
      "objectives": "संकल्पना व उद्दिष्टे सराव.",
      "activity": "विविध कृती व उपक्रम."
    },
    "January": {
      "topic": "२० . आपले वाचनालय * एकदा गंमत झाली (चित्रकथा) \n२१. भेट         ९.१ / ९.१.२ / ९.२ \n२२. सिरीज सिरीज रे !( कविता). ९.१ / ९.१.२ / ९.२ \n२३. कोल्हा आणि करकोचा",
      "objectives": "संकल्पना व उद्दिष्टे सराव.",
      "activity": "विविध कृती व उपक्रम."
    },
    "February": {
      "topic": "२४. हत्तीचे गर्वहरण.   १०.५ / १०.५.२ \nअतिरिक्त पूरक मार्गदर्शन तसेच सराव \nद्वितीय सत्र संकलित मूल्यमापन.२",
      "objectives": "संकल्पना व उद्दिष्टे सराव.",
      "activity": "विविध कृती व उपक्रम."
    },
    "March": {
      "topic": "अतिरिक्त पूरक मार्गदर्शन तसेच सराव",
      "objectives": "संकल्पना व उद्दिष्टे सराव.",
      "activity": "विविध कृती व उपक्रम."
    },
    "April": {
      "topic": "—",
      "objectives": "संकल्पना व उद्दिष्टे सराव.",
      "activity": "विविध कृती व उपक्रम."
    },
    "May": {
      "topic": "—",
      "objectives": "संकल्पना व उद्दिष्टे सराव.",
      "activity": "विविध कृती व उपक्रम."
    }
  },
  "math_mr": {
    "June": {
      "topic": "वर्ग पूर्वतयारी अभ्यासक्रम \nवर्ग पूर्वतयारी अभ्यासक्रम \n* चला शोधूया वेगवेगळे आकार \n* चला हाताळूया भौमितिक आकार  * गंमत रेषेची",
      "objectives": "संकल्पना व उद्दिष्टे सराव.",
      "activity": "विविध कृती व उपक्रम."
    },
    "July": {
      "topic": "* चला ओळखूया भौमितिक आकृत्या  * संख्यांच्या जगात \n* संख्या वाचू - लिहूया \n* गट करून मोजणी. *  चित्रात दाखवलेली संख्या \n* स्थानिक किंमत म्हणजे काय    * संख्येचे विस्तारित रूप",
      "objectives": "संकल्पना व उद्दिष्टे सराव.",
      "activity": "विविध कृती व उपक्रम."
    },
    "August": {
      "topic": "* टप्प्याने संख्या मोजूया  *बेरजेची गंमत \nप्रथम घटक चाचणी \n* बेरीज पुढे मोजून  * बेरीज बिनहातच्याची \n* शून्याची बेरीज आणि वजाबाकी",
      "objectives": "संकल्पना व उद्दिष्टे सराव.",
      "activity": "विविध कृती व उपक्रम."
    },
    "September": {
      "topic": "* गोष्टीतील बेरीज १ \n* वजाबाकी ने कमी करूया \n*बेरीज- वजाबाकी जोडी  * गोष्टीतील वजाबाकी \n* वर्षाचे महिने बारा",
      "objectives": "संकल्पना व उद्दिष्टे सराव.",
      "activity": "विविध कृती व उपक्रम."
    },
    "October": {
      "topic": "अतिरिक्त पूरक मार्गदर्शन तसेच सराव \nप्रथम सत्र संकलित मूल्यमापन क्र.१ \nदिवाळी सुट्ट्या \n* संख्यांचा लहान मोठेपणा * संख्यांचा चढता व उतरता क्रम",
      "objectives": "संकल्पना व उद्दिष्टे सराव.",
      "activity": "विविध कृती व उपक्रम."
    },
    "November": {
      "topic": "*संख्येचे शेजारी : लगतची मागची व पुढची संख्या \n*चला संख्या तयार करूया \n*संख्यावाचक ( मूल्यवाचक ) क्रमवाचक शब्द \n* मिळवू चित्रातून माहिती  * खास बेरीज हातच्याची",
      "objectives": "संकल्पना व उद्दिष्टे सराव.",
      "activity": "विविध कृती व उपक्रम."
    },
    "December": {
      "topic": "* गोष्टीतील बेरीज - २ \n* वजाबाकी साठी दशक सुटा करू \n* ओळखूया नाणी नोटा  * लांबी मोजूया \nद्वितीय घटक चाचणी",
      "objectives": "संकल्पना व उद्दिष्टे सराव.",
      "activity": "विविध कृती व उपक्रम."
    },
    "January": {
      "topic": "* वजन करूया \n* धारकता मोजुया \n* माहितीचे व्यवस्थापन \n* आकृतीबंध.  * गुणाकार पूर्वतयारी",
      "objectives": "संकल्पना व उद्दिष्टे सराव.",
      "activity": "विविध कृती व उपक्रम."
    },
    "February": {
      "topic": "* पाढे तयार करूया.      * गोष्टीतील गणित \nद्वितीय सत्र संकलित मूल्यमापन क्र.२ \nअतिरिक्त पूरक मार्गदर्शन तसेच सराव \nपाढे पाठांतर सराव",
      "objectives": "संकल्पना व उद्दिष्टे सराव.",
      "activity": "विविध कृती व उपक्रम."
    },
    "March": {
      "topic": "—",
      "objectives": "संकल्पना व उद्दिष्टे सराव.",
      "activity": "विविध कृती व उपक्रम."
    },
    "April": {
      "topic": "—",
      "objectives": "संकल्पना व उद्दिष्टे सराव.",
      "activity": "विविध कृती व उपक्रम."
    },
    "May": {
      "topic": "—",
      "objectives": "संकल्पना व उद्दिष्टे सराव.",
      "activity": "विविध कृती व उपक्रम."
    }
  },
  "english": {
    "June": {
      "topic": "Preparation of class *  Revision \n(Unit one ).   1.1 welcome to school \n1.2 Back to school    1.3  Let's play the game \n1.4 World of the alphabet.  1.5 A feast in the forest",
      "objectives": "संकल्पना व उद्दिष्टे सराव.",
      "activity": "विविध कृती व उपक्रम."
    },
    "July": {
      "topic": "1.6 Big' A 'Small 'a' \n1.7 Fruit salad \n1.8 Number song \n1.9 Introduce yourself",
      "objectives": "संकल्पना व उद्दिष्टे सराव.",
      "activity": "विविध कृती व उपक्रम."
    },
    "August": {
      "topic": "1.10 Sounds - I.       1.11 Open the treasure \nUnit Two \n2.1 It's raining.       2.2 what the whether say? \n2.3 A visit to form.   2.4 In the park",
      "objectives": "संकल्पना व उद्दिष्टे सराव.",
      "activity": "विविध कृती व उपक्रम."
    },
    "September": {
      "topic": "Revision \nFirst unit test \n2.5 A joyful trip    2.6Music store \n2.7 The story of flute",
      "objectives": "संकल्पना व उद्दिष्टे सराव.",
      "activity": "विविध कृती व उपक्रम."
    },
    "October": {
      "topic": "2.8 Tring Tring.        2.9 Origami \n2.10 sound - II.       2.11 Open the treasure \nRevision \nFirst term exam",
      "objectives": "संकल्पना व उद्दिष्टे सराव.",
      "activity": "विविध कृती व उपक्रम."
    },
    "November": {
      "topic": "Diwali vacation \nRevision \nUnit three \n3.1 Where is it.    3.2 Our calendar",
      "objectives": "संकल्पना व उद्दिष्टे सराव.",
      "activity": "विविध कृती व उपक्रम."
    },
    "December": {
      "topic": "3.3 Treasure hunt.            3.4 India \n3.5 Clock and me.    3.6 Birthday celebration \n3.7 My robot.         3.8 Genia Vs.Mr Germ \n3.9 Talking marks.     3.10 sounds - III",
      "objectives": "संकल्पना व उद्दिष्टे सराव.",
      "activity": "विविध कृती व उपक्रम."
    },
    "January": {
      "topic": "3.11 Open the treasure \nRevision \nUnit Four \n4.1 Read a book.       4.2 In the market",
      "objectives": "संकल्पना व उद्दिष्टे सराव.",
      "activity": "विविध कृती व उपक्रम."
    },
    "February": {
      "topic": "Second unit test \n4.3 Good habits.     4.4 Five senses \n4.5 Magic  words. 4.6 Rahi : The girl who never give up ! \n4.7 Mother duck. 4.8 Story time",
      "objectives": "संकल्पना व उद्दिष्टे सराव.",
      "activity": "विविध कृती व उपक्रम."
    },
    "March": {
      "topic": "4.9 Grow a little plant. 4.10 Alphabet train \n4.11 Open the treasure",
      "objectives": "संकल्पना व उद्दिष्टे सराव.",
      "activity": "विविध कृती व उपक्रम."
    },
    "April": {
      "topic": "Practice examples \nSecond term exam \nPractice and revision",
      "objectives": "संकल्पना व उद्दिष्टे सराव.",
      "activity": "विविध कृती व उपक्रम."
    },
    "May": {
      "topic": "—",
      "objectives": "संकल्पना व उद्दिष्टे सराव.",
      "activity": "विविध कृती व उपक्रम."
    }
  },
  "art": {
    "June": {
      "topic": "वर्ग पूर्वतयारी अभ्यासक्रम \n* बडबडगीत  * गाण्याच्या ठेक्यावर उपलब्ध साधनांचे वादन टाळ \n* चित्र             * रेखाटन -  रंग व छटा \n* शिल्प             * मुद्राचित्र - कोलाज काम",
      "objectives": "संकल्पना व उद्दिष्टे सराव.",
      "activity": "विविध कृती व उपक्रम."
    },
    "July": {
      "topic": "* गायन            * नाट्य -  कथा व संगीत \n* वादन            * संगीत \n*चित्र              *चिकटकाम \n* नृत्य            * शौर्यगीत",
      "objectives": "संकल्पना व उद्दिष्टे सराव.",
      "activity": "विविध कृती व उपक्रम."
    },
    "August": {
      "topic": "*नाट्य          * संगीत \nप्रथम घटक चाचणी \n*गायन, वादन.        * उपलब्ध साधनांचा उपयोग \n* वादन               * संगीत व अभिनय",
      "objectives": "संकल्पना व उद्दिष्टे सराव.",
      "activity": "विविध कृती व उपक्रम."
    },
    "September": {
      "topic": "* चित्र - शिल्प        *रंगकाम व मुखवट्यांचा वापर \n* चित्र - शिल्प -  स्मरणचित्र  मुद्रा चित्र \n* चित्र.              *  निसर्गचित्र  व चित्र रंगवणे \n* नाट्य            * प्रसंगारूप अभिनय",
      "objectives": "संकल्पना व उद्दिष्टे सराव.",
      "activity": "विविध कृती व उपक्रम."
    },
    "October": {
      "topic": "*वादन            * विविध वाद्यांची ओळख \nप्रथम सत्र संकलित मूल्यमापन क्र.१ \nदिवाळी सुट्ट्या \nअतिरिक्त मार्गदर्शन तसेच सराव व समृद्धी",
      "objectives": "संकल्पना व उद्दिष्टे सराव.",
      "activity": "विविध कृती व उपक्रम."
    },
    "November": {
      "topic": "* चित्र व शिल्प            * फुलपाखरू व पणती बनवणे \n* नृत्य व गायन  - मूक अभिनय व गायन \n*चित्र व शिल्प -  कोलाज ,नक्षीकाम ,चिकटकाम \n*संगीत - डिजिटल माध्यमांचे सादरीकरण",
      "objectives": "संकल्पना व उद्दिष्टे सराव.",
      "activity": "विविध कृती व उपक्रम."
    },
    "December": {
      "topic": "*शिल्प - ठसेकाम व माती पासून विविध वस्तू तयार करणे \n*गायन व नृत्य - समूह गायन व देशभक्तीपर गीत गायन \n* नाट्य - नाटक व नृत्यांचा सराव \nद्वितीय घटक चाचणी",
      "objectives": "संकल्पना व उद्दिष्टे सराव.",
      "activity": "विविध कृती व उपक्रम."
    },
    "January": {
      "topic": "* चित्र व शिल्प - रंगकाम व त्रिमितीय आकारांची निर्मिती \n* नाट्य -  प्रसंग सादरीकरण व प्राण्यांमधील संवाद \n*गायन - बडबडगीत \n* नृत्य  - अभिनय चित्रफित",
      "objectives": "संकल्पना व उद्दिष्टे सराव.",
      "activity": "विविध कृती व उपक्रम."
    },
    "February": {
      "topic": "अतिरिक्त मार्गदर्शन तसेच सराव व समृद्धी \nअतिरिक्त मार्गदर्शन तसेच सराव समृद्धी \nद्वितीय सत्र संकलित मूल्यमापन क्र.२ \nसराव व अभ्यासक्रम",
      "objectives": "संकल्पना व उद्दिष्टे सराव.",
      "activity": "विविध कृती व उपक्रम."
    },
    "March": {
      "topic": "—",
      "objectives": "संकल्पना व उद्दिष्टे सराव.",
      "activity": "विविध कृती व उपक्रम."
    },
    "April": {
      "topic": "—",
      "objectives": "संकल्पना व उद्दिष्टे सराव.",
      "activity": "विविध कृती व उपक्रम."
    },
    "May": {
      "topic": "—",
      "objectives": "संकल्पना व उद्दिष्टे सराव.",
      "activity": "विविध कृती व उपक्रम."
    }
  },
  "work": {
    "June": {
      "topic": "वर्ग पूर्वतयारी अभ्यासक्रम \nवर्ग पूर्वतयारी अभ्यासक्रम \n१. गरजाधीष्टीत उपक्रम.      १.१ पाऊस \n(अ) संस्कृती आणि कार्य जगताची ओळख.       १.२ कार्य जगत",
      "objectives": "संकल्पना व उद्दिष्टे सराव.",
      "activity": "विविध कृती व उपक्रम."
    },
    "July": {
      "topic": "१.३ परिसराची ओळख \n१.४ वर्ग सुशोभन \n१.५ पाणी पिण्याच्या पद्धती \n(ब ) जलप्रवाह",
      "objectives": "संकल्पना व उद्दिष्टे सराव.",
      "activity": "विविध कृती व उपक्रम."
    },
    "August": {
      "topic": "(क ) आपत्ती व्यवस्थापन \nप्रथम घटक चाचणी \n२. अभिरुची पूरक उपक्रम.    (अ) रंगीत कागद \n(ब ) रांगोळी",
      "objectives": "संकल्पना व उद्दिष्टे सराव.",
      "activity": "विविध कृती व उपक्रम."
    },
    "September": {
      "topic": "(क ) संग्रह \n(ड ) काड्यांपासून आकार \n३. कौशल्याधिष्ठित उपक्रम. (अ) नैसर्गिक वस्तूंचे ठसे \n(ब ) कागदी पंखा तयार करणे",
      "objectives": "संकल्पना व उद्दिष्टे सराव.",
      "activity": "विविध कृती व उपक्रम."
    },
    "October": {
      "topic": "सराव व उपचार \nप्रथम सत्र संकलित मूल्यमापन क्र.१ \nदिवाळी सुट्ट्या \nअतिरिक्त पूरक मार्गदर्शन तसेच सराव",
      "objectives": "संकल्पना व उद्दिष्टे सराव.",
      "activity": "विविध कृती व उपक्रम."
    },
    "November": {
      "topic": "४. ऐच्छिक उपक्रम.        १.१ परसातील बागकाम \n(अ ) उत्पादक क्षेत्र.  १.२ कुंडीतील लागवड \n(१) क्षेत्र : अन्न.     १.३ कुंडीचे आकार आणि रोपे यांची ओळख \n१.४ फळप्रक्रिया         १.५ मत्स्य व्यवसाय",
      "objectives": "संकल्पना व उद्दिष्टे सराव.",
      "activity": "विविध कृती व उपक्रम."
    },
    "December": {
      "topic": "(२) क्षेत्र : वस्त्र.       २.१ वस्त्र निर्मिती \n२.२ प्राथमिक शिवणकाम \n२.३ बाहुलीकाम     २.४ काद्याचे विणकाम \nद्वितीय घटक चाचणी",
      "objectives": "संकल्पना व उद्दिष्टे सराव.",
      "activity": "विविध कृती व उपक्रम."
    },
    "January": {
      "topic": "(३) क्षेत्र : निवारा.      ३.१ मातकाम \n३.२ बांबूकाम व वेतकाम \n३.३ फुलझाडांची व शोभिवंत झाडांची लागवड \n(क ) इतर क्षेत्र.      शेतीपूरक व्यवसाय (पशुपक्षी संवर्धन)",
      "objectives": "संकल्पना व उद्दिष्टे सराव.",
      "activity": "विविध कृती व उपक्रम."
    },
    "February": {
      "topic": "५. तंत्रज्ञान क्षेत्र.      (ब ) माहिती व संप्रेषण तंत्रज्ञान \nद्वितीय सत्र संकलित मूल्यमापन क्र.२ \nअतिरिक्त पूरक मार्गदर्शन तसेच सराव",
      "objectives": "संकल्पना व उद्दिष्टे सराव.",
      "activity": "विविध कृती व उपक्रम."
    },
    "March": {
      "topic": "—",
      "objectives": "संकल्पना व उद्दिष्टे सराव.",
      "activity": "विविध कृती व उपक्रम."
    },
    "April": {
      "topic": "—",
      "objectives": "संकल्पना व उद्दिष्टे सराव.",
      "activity": "विविध कृती व उपक्रम."
    },
    "May": {
      "topic": "—",
      "objectives": "संकल्पना व उद्दिष्टे सराव.",
      "activity": "विविध कृती व उपक्रम."
    }
  },
  "pe": {
    "June": {
      "topic": "वर्ग पूर्वतयारी अभ्यासक्रम \nयोगा दिन व वैयक्तिक स्वच्छता \n(भाग -१ ) ०.१ आरोग्य * आरोग्यधिष्टित शारीरिक सुदृढता \n०.२ विविध हालचाली व योग्य शारीरिक स्थिती",
      "objectives": "संकल्पना व उद्दिष्टे सराव.",
      "activity": "विविध कृती व उपक्रम."
    },
    "July": {
      "topic": "* शारीरिक विषयक जाण    *योग्य शरीर स्थिती व हालचाली सराव \n०.३ खेळ व शर्यती.   * उपक्रम योगाभ्यास शर्यती व खेळ \n* शारीरिक विषयक जाण - उपक्रम \n०.४ कौशल्यात्मक उपक्रम *कारक सुदृढता- उपक्रम योगाभ्यास",
      "objectives": "संकल्पना व उद्दिष्टे सराव.",
      "activity": "विविध कृती व उपक्रम."
    },
    "August": {
      "topic": "०.५ व्यायाम  * स्नायूंना उत्तेजित करण्यासाठी योग्य व्यायाम \nप्रथम घटक चाचणी \n(भाग - २ ) ०.१ आरोग्य *आरोग्यधिष्टित शारीरिक सुदृढता \n०.२  विविध हालचाली व योग्य शारीरिक स्थिती",
      "objectives": "संकल्पना व उद्दिष्टे सराव.",
      "activity": "विविध कृती व उपक्रम."
    },
    "September": {
      "topic": "* शारीरिक विषयक जाण \n* आरोग्यधिष्टित शारीरिक सुदृढता \n०.३ खेळ व शर्यती * उपक्रम योगाभ्यास शर्यती व खेळ \n०.४ कौशल्यात्मक उपक्रम  * कौशल्यात्मक उपक्रमांचा सराव घेणे",
      "objectives": "संकल्पना व उद्दिष्टे सराव.",
      "activity": "विविध कृती व उपक्रम."
    },
    "October": {
      "topic": "अतिरिक्त मार्गदर्शन व सराव \nप्रथम सत्र संकलित मूल्यमापन क्र.१ \nदिवाळी सुट्ट्या \n०.५ व्यायाम * स्नायूंना उत्तेजित करण्यासाठी योग्य व्यायाम",
      "objectives": "संकल्पना व उद्दिष्टे सराव.",
      "activity": "विविध कृती व उपक्रम."
    },
    "November": {
      "topic": "अतिरिक्त मार्गदर्शन व सराव \n(भाग - ३ ) ०.१ आरोग्य * आरोग्य दृष्टीत शारीरिक सुदृढता \n०.२ विविध हालचाली व योग्य शारीरिक स्थिती \n* आरोग्यधिष्टित शारीरिक सुदृढता आसन क्रमांक एक",
      "objectives": "संकल्पना व उद्दिष्टे सराव.",
      "activity": "विविध कृती व उपक्रम."
    },
    "December": {
      "topic": "०.३ खेळ व शर्यती *. उपक्रम योगाभ्यास शर्यती व खेळ \n०.४ कौशल्यात्मक उपक्रम. * कौशल्यात्मक उपक्रमांचा सराव घेणे \n०.५ व्यायाम * स्नायूंना उत्तेजित करण्यासाठी योग्य व्यायाम \nद्वितीय घटक चाचणी",
      "objectives": "संकल्पना व उद्दिष्टे सराव.",
      "activity": "विविध कृती व उपक्रम."
    },
    "January": {
      "topic": "(भाग - ४ ) ०.१ आरोग्य. * आरोग्यधिष्टीत शारीरिक सदृढता \n* आरोग्यधिष्टीत शारीरिक सदृढता \n०.२ विविध हालचाली व योग्य शारीरिक स्थिती \n* शारीरिक विषयक जाण",
      "objectives": "संकल्पना व उद्दिष्टे सराव.",
      "activity": "विविध कृती व उपक्रम."
    },
    "February": {
      "topic": "०.३ खेळ व शर्यती * उपक्रम योगाभ्यास शर्यती व खेळ \n०.४ कौशल्यात्मक उपक्रम. * कौशल्यात्मक उपक्रमांचा सराव घेणे \n०.५ व्यायाम * स्नायूंना उत्तेजित करण्यासाठी योग्य व्यायाम \nद्वितीय सत्र संकलित मूल्यमापन क्र . २",
      "objectives": "संकल्पना व उद्दिष्टे सराव.",
      "activity": "विविध कृती व उपक्रम."
    },
    "March": {
      "topic": "—",
      "objectives": "संकल्पना व उद्दिष्टे सराव.",
      "activity": "विविध कृती व उपक्रम."
    },
    "April": {
      "topic": "—",
      "objectives": "संकल्पना व उद्दिष्टे सराव.",
      "activity": "विविध कृती व उपक्रम."
    },
    "May": {
      "topic": "—",
      "objectives": "संकल्पना व उद्दिष्टे सराव.",
      "activity": "विविध कृती व उपक्रम."
    }
  },
  "math_en": {
    "June": {
      "topic": "Preparation of class \nRevision \n* let's find the shapes ! *let's handle geometric shapes \n* fun with line.   *let's identify geometrical shapes",
      "objectives": "संकल्पना व उद्दिष्टे सराव.",
      "activity": "विविध कृती व उपक्रम."
    },
    "July": {
      "topic": "* In the world of numbers \n*let's read and write in words \n* counting in groups.      *number given in a picture \n* what is the meaning of ' place value '?",
      "objectives": "संकल्पना व उद्दिष्टे सराव.",
      "activity": "विविध कृती व उपक्रम."
    },
    "August": {
      "topic": "* The expanded form of a number \n* let's count numbers in steps \n*fun with addition \nfirst unit test",
      "objectives": "संकल्पना व उद्दिष्टे सराव.",
      "activity": "विविध कृती व उपक्रम."
    },
    "September": {
      "topic": "* Addition by counting forward \n* Addition- without carry over \n* Addition and subtraction of zero \n* Stories of addition - 1.     * Twelve months in a year",
      "objectives": "संकल्पना व उद्दिष्टे सराव.",
      "activity": "विविध कृती व उपक्रम."
    },
    "October": {
      "topic": "Practice and revision \nFirst term exam \nDiwali vacation \n* Comparing numbers.    * Neighbouring no. on each side",
      "objectives": "संकल्पना व उद्दिष्टे सराव.",
      "activity": "विविध कृती व उपक्रम."
    },
    "November": {
      "topic": "* Ascending and descending order of numbers \n* Come let's make numbers \n* Cardinal numbers are ordinal numbers \n* Reading pictures",
      "objectives": "संकल्पना व उद्दिष्टे सराव.",
      "activity": "विविध कृती व उपक्रम."
    },
    "December": {
      "topic": "* A special way to add - by carrying over \n* Stories of addition -2 \n* let's untie a 10 in order to subtract \n* Do you know notes and coins ?",
      "objectives": "संकल्पना व उद्दिष्टे सराव.",
      "activity": "विविध कृती व उपक्रम."
    },
    "January": {
      "topic": "* let's measure length \nSecond unit test \n* let's weigh           * let's measure capacity \n* Managing information",
      "objectives": "संकल्पना व उद्दिष्टे सराव.",
      "activity": "विविध कृती व उपक्रम."
    },
    "February": {
      "topic": "* patterns \n*Multiplication preparation \n* let's make tables.      * Maths in a story \nRevision",
      "objectives": "संकल्पना व उद्दिष्टे सराव.",
      "activity": "विविध कृती व उपक्रम."
    },
    "March": {
      "topic": "Practice examples \nSecond term exam \nPractice and revision",
      "objectives": "संकल्पना व उद्दिष्टे सराव.",
      "activity": "विविध कृती व उपक्रम."
    },
    "April": {
      "topic": "—",
      "objectives": "संकल्पना व उद्दिष्टे सराव.",
      "activity": "विविध कृती व उपक्रम."
    },
    "May": {
      "topic": "—",
      "objectives": "संकल्पना व उद्दिष्टे सराव.",
      "activity": "विविध कृती व उपक्रम."
    }
  }
}
